odoo/addons/analytic_operating_unit/README.rst
odoo/addons/analytic_operating_unit/__init__.py
odoo/addons/analytic_operating_unit/__manifest__.py
odoo/addons/analytic_operating_unit/i18n/analytic_operating_unit.pot
odoo/addons/analytic_operating_unit/i18n/es_AR.po
odoo/addons/analytic_operating_unit/i18n/es_MX.po
odoo/addons/analytic_operating_unit/i18n/it.po
odoo/addons/analytic_operating_unit/models/__init__.py
odoo/addons/analytic_operating_unit/models/account_analytic_account.py
odoo/addons/analytic_operating_unit/readme/CONTRIBUTORS.md
odoo/addons/analytic_operating_unit/readme/DESCRIPTION.md
odoo/addons/analytic_operating_unit/readme/USAGE.md
odoo/addons/analytic_operating_unit/security/analytic_account_security.xml
odoo/addons/analytic_operating_unit/static/description/icon.png
odoo/addons/analytic_operating_unit/static/description/index.html
odoo/addons/analytic_operating_unit/static/src/components/analytic_distribution.esm.js
odoo/addons/analytic_operating_unit/views/analytic_account_view.xml
odoo_addon_analytic_operating_unit-18.0.1.0.0.2.dist-info/METADATA
odoo_addon_analytic_operating_unit-18.0.1.0.0.2.dist-info/WHEEL
odoo_addon_analytic_operating_unit-18.0.1.0.0.2.dist-info/top_level.txt
odoo_addon_analytic_operating_unit-18.0.1.0.0.2.dist-info/RECORD
